MANIFEST.in
README.rst
setup.cfg
setup.py
collective/__init__.py
collective.jsconfiguration.egg-info/PKG-INFO
collective.jsconfiguration.egg-info/SOURCES.txt
collective.jsconfiguration.egg-info/dependency_links.txt
collective.jsconfiguration.egg-info/entry_points.txt
collective.jsconfiguration.egg-info/namespace_packages.txt
collective.jsconfiguration.egg-info/not-zip-safe
collective.jsconfiguration.egg-info/requires.txt
collective.jsconfiguration.egg-info/top_level.txt
collective/jsconfiguration/__init__.py
collective/jsconfiguration/configure.zcml
collective/jsconfiguration/interfaces.py
collective/jsconfiguration/testing.py
collective/jsconfiguration/browser/__init__.py
collective/jsconfiguration/browser/configure.zcml
collective/jsconfiguration/browser/viewlet.pt
collective/jsconfiguration/browser/viewlet.py
collective/jsconfiguration/tests/__init__.py
collective/jsconfiguration/tests/test_dom.pt
collective/jsconfiguration/tests/test_dom.py
collective/jsconfiguration/tests/test_js_object.py
collective/jsconfiguration/tests/test_json.py
docs/HISTORY.rst
docs/INSTALL.txt
docs/LICENSE.GPL
docs/LICENSE.txt