Metadata-Version: 1.0
Name: collective.jsconfiguration
Version: 0.1.1
Summary: General approach for adding JavaScript configuration (and i18n data) to Plone products
Home-page: https://github.com/keul/collective.jsconfiguration
Author: keul
Author-email: luca@keul.it
License: GPL
Keywords: plone javascript configuration i18n
Platform: UNKNOWN
Classifier: Framework :: Plone
Classifier: Framework :: Plone :: 4.2
Classifier: Framework :: Plone :: 4.3
Classifier: Programming Language :: Python
Classifier: Intended Audience :: Developers
